setup.cfg
setup.py
lanchat/__init__.py
lanchat/chat.py
lanchat/cli.py
lanchat/client.py
lanchat/config.py
lanchat/error.py
lanchat/server.py
lanchat/utils.py
lanchat.egg-info/PKG-INFO
lanchat.egg-info/SOURCES.txt
lanchat.egg-info/dependency_links.txt
lanchat.egg-info/entry_points.txt
lanchat.egg-info/not-zip-safe
lanchat.egg-info/top_level.txt