Metadata-Version: 1.1
Name: lanchat
Version: 0.0.7
Summary: Distributed LAN chat
Home-page: https://github.com/theSage21/lanchat
Author: Arjoonn Sharma
Author-email: Arjoonn Sharma
License: MIT
Keywords: LAN,chat,serverless
Platform: UNKNOWN
Classifier: Development Status :: 4 - Beta
Classifier: Intended Audience :: Developers
Classifier: License :: OSI Approved :: MIT License
Classifier: Programming Language :: Python :: 3.4
